codeforces/__init__.py
codeforces/api/__init__.py
codeforces/api/codeforces_api.py
codeforces/api/json_objects/__init__.py
codeforces/api/json_objects/base_json_object.py
codeforces/api/json_objects/contest.py
codeforces/api/json_objects/hack.py
codeforces/api/json_objects/judge_protocol.py
codeforces/api/json_objects/member.py
codeforces/api/json_objects/party.py
codeforces/api/json_objects/problem.py
codeforces/api/json_objects/problem_result.py
codeforces/api/json_objects/problem_statistics.py
codeforces/api/json_objects/ranklist_row.py
codeforces/api/json_objects/rating_change.py
codeforces/api/json_objects/submission.py
codeforces/api/json_objects/user.py
codeforces/utils/__init__.py
codeforces/utils/lazy_property.py
codeforces_api-0.3.1.dist-info/DESCRIPTION.rst
codeforces_api-0.3.1.dist-info/METADATA
codeforces_api-0.3.1.dist-info/RECORD
codeforces_api-0.3.1.dist-info/WHEEL
codeforces_api-0.3.1.dist-info/metadata.json
codeforces_api-0.3.1.dist-info/top_level.txt
