Metadata-Version: 2.0
Name: codeforces-api
Version: 0.3.1
Summary: Wrapper library for Codeforces API
Home-page: https://github.com/soon/CodeforcesAPI
Author: Andrew Kuchev
Author-email: 0coming.soon@gmail.com
License: MIT
Keywords: codeforces api wrapper
Platform: UNKNOWN
Classifier: Development Status :: 4 - Beta
Classifier: Environment :: Console
Classifier: License :: OSI Approved :: MIT License
Classifier: Operating System :: OS Independent
Classifier: Programming Language :: Python :: 3
Classifier: Topic :: Utilities
Requires-Dist: enum34
